[
    {
      "id": "5e4d58d57faa6521dd62b1c0",
      "model": 1,
      "responseTime": 104,
      "statusCode": 403,
      "timestamp": 1580364336
    },
    {
      "id": "5e4d58d54498e09e0780280d",
      "model": 4,
      "responseTime": 44,
      "statusCode": 403,
      "timestamp": 1578636847
    },
    {
      "id": "5e4d58d5524459314afa5332",
      "model": 2,
      "responseTime": 65,
      "statusCode": 403,
      "timestamp": 1579720049
    },
    {
      "id": "5e4d58d572c584396493cc99",
      "model": 3,
      "responseTime": 277,
      "statusCode": 200,
      "timestamp": 1578957864
    },
    {
      "id": "5e4d58d5bbb7685c1f99d758",
      "model": 4,
      "responseTime": 256,
      "statusCode": 200,
      "timestamp": 1579492810
    },
    {
      "id": "5e4d58d528ca5d82a2a30afa",
      "model": 2,
      "responseTime": 114,
      "statusCode": 200,
      "timestamp": 1578215550
    },
    {
      "id": "5e4d58d52e34556d3b113024",
      "model": 5,
      "responseTime": 65,
      "statusCode": 200,
      "timestamp": 1578117183
    },
    {
      "id": "5e4d58d5055b6b441e39e027",
      "model": 5,
      "responseTime": 256,
      "statusCode": 403,
      "timestamp": 1578748753
    },
    {
      "id": "5e4d58d5e51a8bd018996208",
      "model": 3,
      "responseTime": 288,
      "statusCode": 200,
      "timestamp": 1578008544
    },
    {
      "id": "5e4d58d555d09231c06d4b8f",
      "model": 3,
      "responseTime": 222,
      "statusCode": 200,
      "timestamp": 1579788844
    },
    {
      "id": "5e4d58d59d1207b8ea613439",
      "model": 4,
      "responseTime": 132,
      "statusCode": 200,
      "timestamp": 1580235366
    },
    {
      "id": "5e4d58d5832ef1106f4d1dba",
      "model": 1,
      "responseTime": 175,
      "statusCode": 403,
      "timestamp": 1579975902
    },
    {
      "id": "5e4d58d53a466216a88c098d",
      "model": 4,
      "responseTime": 65,
      "statusCode": 403,
      "timestamp": 1580205470
    },
    {
      "id": "5e4d58d59f01552c50e61188",
      "model": 2,
      "responseTime": 61,
      "statusCode": 403,
      "timestamp": 1579376897
    },
    {
      "id": "5e4d58d57c8ef43c8d96fceb",
      "model": 3,
      "responseTime": 98,
      "statusCode": 200,
      "timestamp": 1578281905
    },
    {
      "id": "5e4d58d54d1e93468ab2598f",
      "model": 3,
      "responseTime": 52,
      "statusCode": 200,
      "timestamp": 1578405351
    },
    {
      "id": "5e4d58d50a89fe9eca92724e",
      "model": 4,
      "responseTime": 175,
      "statusCode": 403,
      "timestamp": 1578744059
    },
    {
      "id": "5e4d58d5ef484d3d9835ff89",
      "model": 2,
      "responseTime": 179,
      "statusCode": 200,
      "timestamp": 1579209147
    },
    {
      "id": "5e4d58d552869e5416fe1391",
      "model": 2,
      "responseTime": 196,
      "statusCode": 200,
      "timestamp": 1579647796
    },
    {
      "id": "5e4d58d5992feedb13425f25",
      "model": 2,
      "responseTime": 109,
      "statusCode": 200,
      "timestamp": 1578656039
    },
    {
      "id": "5e4d58d5623b43e67cf6ecc3",
      "model": 1,
      "responseTime": 211,
      "statusCode": 200,
      "timestamp": 1579368248
    },
    {
      "id": "5e4d58d5e8da542a11760f50",
      "model": 2,
      "responseTime": 246,
      "statusCode": 200,
      "timestamp": 1580015614
    },
    {
      "id": "5e4d58d551fd6a3d44e364ea",
      "model": 3,
      "responseTime": 84,
      "statusCode": 403,
      "timestamp": 1578863881
    },
    {
      "id": "5e4d58d544d21911dcadcca7",
      "model": 3,
      "responseTime": 138,
      "statusCode": 200,
      "timestamp": 1578921675
    },
    {
      "id": "5e4d58d546519b062d7f5a56",
      "model": 2,
      "responseTime": 129,
      "statusCode": 200,
      "timestamp": 1579508504
    },
    {
      "id": "5e4d58d5caab29c568d51c30",
      "model": 2,
      "responseTime": 63,
      "statusCode": 200,
      "timestamp": 1577922952
    },
    {
      "id": "5e4d58d5d59a39e00db00803",
      "model": 3,
      "responseTime": 52,
      "statusCode": 403,
      "timestamp": 1578709435
    },
    {
      "id": "5e4d58d5aca62650e38a0ff8",
      "model": 3,
      "responseTime": 291,
      "statusCode": 200,
      "timestamp": 1578997454
    },
    {
      "id": "5e4d58d5f333f66aa3c2d0a3",
      "model": 4,
      "responseTime": 168,
      "statusCode": 403,
      "timestamp": 1579757657
    },
    {
      "id": "5e4d58d5d9757ba8f2de1021",
      "model": 5,
      "responseTime": 297,
      "statusCode": 200,
      "timestamp": 1579759763
    },
    {
      "id": "5e4d58d52d8bc960b893f64a",
      "model": 2,
      "responseTime": 134,
      "statusCode": 403,
      "timestamp": 1578560434
    },
    {
      "id": "5e4d58d5934d5a70900c0bc8",
      "model": 5,
      "responseTime": 150,
      "statusCode": 200,
      "timestamp": 1578209871
    },
    {
      "id": "5e4d58d5ddc5378554f0d71d",
      "model": 4,
      "responseTime": 112,
      "statusCode": 200,
      "timestamp": 1578588314
    },
    {
      "id": "5e4d58d5822a80d25199f6f6",
      "model": 2,
      "responseTime": 240,
      "statusCode": 200,
      "timestamp": 1579655736
    },
    {
      "id": "5e4d58d5d2fd70a87cd3d427",
      "model": 1,
      "responseTime": 142,
      "statusCode": 403,
      "timestamp": 1579577991
    },
    {
      "id": "5e4d58d5ed54d57769de3384",
      "model": 2,
      "responseTime": 135,
      "statusCode": 200,
      "timestamp": 1579110661
    },
    {
      "id": "5e4d58d54e18e353bb48bb32",
      "model": 4,
      "responseTime": 148,
      "statusCode": 200,
      "timestamp": 1577994790
    },
    {
      "id": "5e4d58d52bccf85f6588890f",
      "model": 4,
      "responseTime": 217,
      "statusCode": 403,
      "timestamp": 1578629826
    },
    {
      "id": "5e4d58d5c7af13a4c645076a",
      "model": 3,
      "responseTime": 288,
      "statusCode": 403,
      "timestamp": 1579303043
    },
    {
      "id": "5e4d58d5b9b6278493f60110",
      "model": 1,
      "responseTime": 274,
      "statusCode": 200,
      "timestamp": 1578661189
    },
    {
      "id": "5e4d58d511595bc8bdf45026",
      "model": 4,
      "responseTime": 189,
      "statusCode": 403,
      "timestamp": 1579471401
    },
    {
      "id": "5e4d58d5a2042e6068641776",
      "model": 3,
      "responseTime": 117,
      "statusCode": 200,
      "timestamp": 1578384480
    },
    {
      "id": "5e4d58d57ef7f2980755afbf",
      "model": 2,
      "responseTime": 50,
      "statusCode": 200,
      "timestamp": 1579390911
    },
    {
      "id": "5e4d58d5b7e82c94e44cc960",
      "model": 5,
      "responseTime": 95,
      "statusCode": 403,
      "timestamp": 1579925940
    },
    {
      "id": "5e4d58d5aeec7cdd8a648dac",
      "model": 1,
      "responseTime": 72,
      "statusCode": 200,
      "timestamp": 1578730985
    },
    {
      "id": "5e4d58d54487b8491be68fe2",
      "model": 1,
      "responseTime": 234,
      "statusCode": 200,
      "timestamp": 1579582531
    },
    {
      "id": "5e4d58d58433fa0aa22a538a",
      "model": 1,
      "responseTime": 66,
      "statusCode": 200,
      "timestamp": 1580407793
    },
    {
      "id": "5e4d58d55cfa0ca7e7ba38bb",
      "model": 1,
      "responseTime": 196,
      "statusCode": 200,
      "timestamp": 1578436210
    },
    {
      "id": "5e4d58d56d6ca0ecfd093c04",
      "model": 5,
      "responseTime": 102,
      "statusCode": 200,
      "timestamp": 1578987487
    },
    {
      "id": "5e4d58d56a45927031b8f95c",
      "model": 2,
      "responseTime": 250,
      "statusCode": 403,
      "timestamp": 1578577086
    }
  ]